commander/README.md
commander/__init__.py
commander/cli.py
commander/config.py
commander/config_loader.py
commander/daemon.py
commander/env_loader.py
commander/instance_manager.py
commander/port_manager.py
commander/project_session.py
commander/registry.py
commander/tmux_orchestrator.py
commander/adapters/README.md
commander/adapters/__init__.py
commander/adapters/auggie.py
commander/adapters/base.py
commander/adapters/claude_code.py
commander/adapters/codex.py
commander/adapters/communication.py
commander/adapters/example_usage.py
commander/adapters/mpm.py
commander/adapters/registry.py
commander/api/__init__.py
commander/api/app.py
commander/api/errors.py
commander/api/schemas.py
commander/api/routes/__init__.py
commander/api/routes/events.py
commander/api/routes/inbox.py
commander/api/routes/messages.py
commander/api/routes/projects.py
commander/api/routes/sessions.py
commander/api/routes/work.py
commander/chat/__init__.py
commander/chat/cli.py
commander/chat/commands.py
commander/chat/repl.py
commander/core/__init__.py
commander/core/block_manager.py
commander/core/response_manager.py
commander/events/__init__.py
commander/events/manager.py
commander/frameworks/__init__.py
commander/frameworks/base.py
commander/frameworks/claude_code.py
commander/frameworks/mpm.py
commander/git/__init__.py
commander/git/worktree_manager.py
commander/inbox/__init__.py
commander/inbox/dedup.py
commander/inbox/inbox.py
commander/inbox/models.py
commander/llm/__init__.py
commander/llm/openrouter_client.py
commander/llm/summarizer.py
commander/memory/README.md
commander/memory/__init__.py
commander/memory/compression.py
commander/memory/embeddings.py
commander/memory/entities.py
commander/memory/example_usage.py
commander/memory/integration.py
commander/memory/search.py
commander/memory/store.py
commander/models/__init__.py
commander/models/events.py
commander/models/project.py
commander/models/work.py
commander/parsing/__init__.py
commander/parsing/extractor.py
ai_commander-0.1.0.dist-info/METADATA
ai_commander-0.1.0.dist-info/WHEEL
ai_commander-0.1.0.dist-info/entry_points.txt
ai_commander-0.1.0.dist-info/licenses/LICENSE
ai_commander-0.1.0.dist-info/RECORD
